{
  "base_price": 1950,
  "beamstation_catalog_url": "https://beamstation.com/datasets",
  "beamstation_origin": "https://beamstation.com",
  "category_group_name": "Restaurants",
  "config_category": "census",
  "config_description": "Local dining market data for Somerville in New England. Filtered by the Restaurants category group, providing business profiles, review counts, contact information, and competitive benchmarks. Refreshed weekly.",
  "config_name": "All Restaurants in Somerville, Massachusetts, US",
  "export_job_id": "0bf86120-7244-42c5-867b-d963a8f86ca8",
  "github_org": "Beamstation-Datasets",
  "id_short": 642652,
  "location_name": "Somerville",
  "location_type": "city",
  "repo_name": "all-restaurants-in-somerville-massachusetts-us-sample-642652",
  "sample_b2_path": "b2-export:BeamStation-ExportFiles/642652/beamstation_642652_restaurants-us-ma_SAMPLE_DIST.csv",
  "sample_pct": 9.62,
  "sample_records": 23,
  "sample_sha256": "b07ca72b15fd125d250510ce35b98c776e5e5f96269acde934f23542123ffc74",
  "sample_size_bytes": 98706,
  "total_records": 239,
  "updated_at": "2026-04-23T10:07:18.181287+00:00"
}